aox/main.py
aox_cli-0.1.5.dist-info/METADATA
aox_cli-0.1.5.dist-info/WHEEL
aox_cli-0.1.5.dist-info/entry_points.txt
aox_cli-0.1.5.dist-info/RECORD
