Metadata-Version: 2.1
Name: aox-cli
Version: 0.1.5
Summary: CLI tool for managing and running AO Counter
Author: Your Name
Author-email: your.email@example.com
Requires-Python: >=3.9,<4.0
Classifier: Programming Language :: Python :: 3
Classifier: Programming Language :: Python :: 3.9
Classifier: Programming Language :: Python :: 3.10
Classifier: Programming Language :: Python :: 3.11
Classifier: Programming Language :: Python :: 3.12
Classifier: Programming Language :: Python :: 3.13
Requires-Dist: ell-ai (>=0.0.14)
Requires-Dist: openai (>=1.54.1)
Requires-Dist: rich (>=13.9.3)
Requires-Dist: typer (>=0.12.5)
